pytest_meilisearch/__init__.py
pytest_meilisearch/_internal.py
pytest_meilisearch/_version.py
pytest_meilisearch/fixtures.py
pytest_meilisearch/plugin.py
pytest_meilisearch-0.6.1.dist-info/METADATA
pytest_meilisearch-0.6.1.dist-info/WHEEL
pytest_meilisearch-0.6.1.dist-info/entry_points.txt
pytest_meilisearch-0.6.1.dist-info/licenses/LICENSE
pytest_meilisearch-0.6.1.dist-info/RECORD
