Metadata-Version: 2.3
Name: pytest-meilisearch
Version: 0.6.1
Summary: Pytest helpers for testing projects using Meilisearch
Author-email: Paul Sanders <paul@paulsanders.dev>
License: MIT License
License-File: LICENSE
Keywords: meilisearch,pytest,python
Classifier: Intended Audience :: Developers
Classifier: License :: OSI Approved :: MIT License
Classifier: Operating System :: OS Independent
Classifier: Programming Language :: Python :: 3.9
Classifier: Programming Language :: Python :: 3.10
Classifier: Programming Language :: Python :: 3.11
Classifier: Programming Language :: Python :: 3.12
Classifier: Programming Language :: Python :: 3.13
Requires-Python: >=3.9
Requires-Dist: meilisearch-python-sdk>=3.0.0
Requires-Dist: pytest>=7.4.3
